dspacelogs/__init__.py
dspacelogs/_analyzer.py
dspacelogs-0.1.6.dist-info/METADATA
dspacelogs-0.1.6.dist-info/WHEEL
dspacelogs-0.1.6.dist-info/top_level.txt
dspacelogs-0.1.6.dist-info/RECORD
