Metadata-Version: 2.4
Name: dspacelogs
Version: 0.1.6
Summary: A simple analyzer for DSpace log files
Author: MatusBeke
Project-URL: Homepage, https://github.com/Matus-Beke/dspacelogs
Classifier: Programming Language :: Python :: 3
Classifier: License :: OSI Approved :: MIT License
Classifier: Operating System :: OS Independent
Classifier: Topic :: System :: Logging
Requires-Python: >=3.8
Requires-Dist: pandas
Requires-Dist: matplotlib
Requires-Dist: seaborn
Provides-Extra: dev
Requires-Dist: pytest; extra == "dev"
